Metadata-Version: 2.4
Name: llama-index-readers-lilac
Version: 0.4.1
Summary: llama-index readers lilac integration
Author-email: Your Name <you@example.com>
Maintainer: nsthorat
License-Expression: MIT
License-File: LICENSE
Requires-Python: <4.0,>=3.9
Requires-Dist: lilac<0.2.0,>=0.1.5
Requires-Dist: llama-index-core<0.15,>=0.13.0
